carlo/__init__.py
carlo/__main__.py
carlo-0.1.9.dist-info/LICENSE
carlo-0.1.9.dist-info/METADATA
carlo-0.1.9.dist-info/WHEEL
carlo-0.1.9.dist-info/entry_points.txt
carlo-0.1.9.dist-info/top_level.txt
carlo-0.1.9.dist-info/RECORD
