Metadata-Version: 2.1
Name: carlo
Version: 0.1.9
Summary: Interactively plot streaming sequences of numbers
Home-page: https://github.com/boppreh/carlo
Author: BoppreH
Author-email: github@boppreh.com
License: UNKNOWN
Project-URL: Bug Tracker, https://github.com/boppreh/carlo/issues
Platform: UNKNOWN
Classifier: Programming Language :: Python :: 3
Classifier: License :: OSI Approved :: MIT License
Classifier: Operating System :: OS Independent
Requires-Python: >=3.6
License-File: LICENSE
Requires-Dist: matplotlib (>=3.4.3)
